lani/__init__.py
lani-0.0.1.dist-info/METADATA
lani-0.0.1.dist-info/WHEEL
lani-0.0.1.dist-info/top_level.txt
lani-0.0.1.dist-info/RECORD
