Metadata-Version: 2.4
Name: lani
Version: 0.0.1
Summary: Dummy lock package for lani
Author: AutoPublisher
